COPYING
MANIFEST.in
lsrsid
setup.py
lsr.SID.egg-info/PKG-INFO
lsr.SID.egg-info/SOURCES.txt
lsr.SID.egg-info/dependency_links.txt
lsr.SID.egg-info/requires.txt
lsr.SID.egg-info/top_level.txt
lsrsidmodules/__init__.py
lsrsidmodules/assistant.py
lsrsidmodules/config.py
lsrsidmodules/constants.py
lsrsidmodules/database.py
lsrsidmodules/database_old.py
lsrsidmodules/events.py
lsrsidmodules/exceptions.py
lsrsidmodules/gui.py
lsrsidmodules/helpers.py
lsrsidmodules/hotkeys.py
lsrsidmodules/libsidutils.py
lsrsidmodules/playlist.py
lsrsidmodules/playsid.py
lsrsidmodules/sidinfo.py
lsrsidmodules/truncate.py
lsrsidmodules/zip.py
lsrsidmodules/glade/assistent.glade
lsrsidmodules/glade/assistent.glade.h
lsrsidmodules/glade/window.glade
lsrsidmodules/glade/window.glade.h
lsrsidmodules/images/IMAGES
lsrsidmodules/images/audio_icon.png
lsrsidmodules/images/badaman_dice.png
lsrsidmodules/images/convert_image.sh
lsrsidmodules/images/star.png
lsrsidmodules/images/star_grey.png
lsrsidmodules/images/XPMs/old_star_grey.xpm
lsrsidmodules/images/XPMs/old_star_yellow.xpm
lsrsidmodules/images/XPMs/star_grey.xpm
lsrsidmodules/images/XPMs/star_yellow.xpm
lsrsidmodules/images/drafts/14.png
lsrsidmodules/images/drafts/192.png
lsrsidmodules/images/drafts/64.png
lsrsidmodules/images/drafts/audio_icon.svg
lsrsidmodules/images/drafts/star.png
lsrsidmodules/images/drafts/star.svg
lsrsidmodules/images/drafts/star_grey.png
lsrsidmodules/images/drafts/star_grey.svg
lsrsidmodules/locale/de_DE/LC_MESSAGES/lsrsid.mo
lsrsidmodules/locale/de_DE/LC_MESSAGES/lsrsid.po
lsrsidmodules/locale/en_US/LC_MESSAGES/lsrsid.mo
lsrsidmodules/starscale/__init__.py
lsrsidmodules/starscale/__init__.pyc
lsrsidmodules/starscale/star.png
lsrsidmodules/starscale/star.svg
lsrsidmodules/starscale/star_grey.png
lsrsidmodules/starscale/star_grey.svg
lsrsidmodules/starscale/star_half_red.svg
lsrsidmodules/starscale/star_red.svg
lsrsidmodules/starscale/xpms.py
lsrsidmodules/starscale/xpms.pyc