Metadata-Version: 1.0
Name: lsr.SID
Version: 0.3
Summary: A SID music database and sidplay frontend
Home-page: UNKNOWN
Author: Daniel Nögel
Author-email: lsrsid@post.danielnoegel.de
License: GPLv3
Keywords: sid sidplay frontend music
Platform: UNKNOWN
Classifier: Development Status :: 4 - Beta
Classifier: Topic :: Multimedia
Classifier: License :: OSI Approved :: GNU General Public License (GPL)
Classifier: Programming Language :: Python
